{
  "packages": [
    {
      "package": {
        "name": "@perlou/large-number",
        "scope": "perlou",
        "version": "1.0.0",
        "description": "大整数加法打包",
        "date": "2022-05-19T09:09:46.943Z",
        "links": {
          "npm": "https://www.npmjs.com/package/%40perlou%2Flarge-number"
        },
        "author": {
          "name": "perlou"
        },
        "publisher": {
          "username": "perlou",
          "email": "perloukevin@gmail.com"
        },
        "maintainers": [
          {
            "username": "perlou",
            "email": "perloukevin@gmail.com"
          }
        ]
      },
      "flags": {
        "insecure": 0
      },
      "score": {
        "final": 0.11806337941351236,
        "detail": {
          "quality": 0.3922700695433172,
          "popularity": 0.001092453001477714,
          "maintenance": 0
        }
      },
      "searchScore": 6.52206e-13
    }
  ],
  "downloads": {
    "@perlou/large-number": 128
  }
}